{
  "id": "validationfail",
  "issue": [
    {
      "code": "structure",
      "details": {
        "text": "Wrong type <class 'int'> for property \"value\" on <class 'fhir.resources.identifier.Identifier'>, expecting <class 'str'>"
      },
      "expression": [
        "generalPractitioner.0.identifier.value"
      ],
      "severity": "error"
    },
    {
      "code": "structure",
      "details": {
        "text": "Wrong type <class 'int'> for property \"value\" on <class 'fhir.resources.identifier.Identifier'>, expecting <class 'str'>"
      },
      "expression": [
        "managingOrganization.identifier.value"
      ],
      "severity": "error"
    }
  ],
  "resourceType": "OperationOutcome"
}